[{"nb_A":3934,"nb_W":342,"nb_implicit_W":2754,"nb_dup_A":946,"nb_dup_W":1,"nb_A_prefix":462,"nb_W_prefix":145,"max_A_prefix":40,"avg_A_prefix":9,"max_A_AS":422,"avg_A_AS":33,"nb_orign_change":154,"nb_new_A":128,"nb_new_A_afterW":106,"max_path_len":18,"avg_path_len":5,"max_editdist":14,"avg_editdist":2,"editdist_7":29,"editdist_8":3,"editdist_9":50,"editdist_10":21,"editdist_11":2,"editdist_12":0,"editdist_13":0,"editdist_14":1,"editdist_15":0,"editdist_16":0,"editdist_17":0,"nb_tolonger":781,"nb_toshorter":1973,"avg_interarrival":1072},{"nb_A":6298,"nb_W":568,"nb_implicit_W":4398,"nb_dup_A":1482,"nb_dup_W":1,"nb_A_prefix":1021,"nb_W_prefix":250,"max_A_prefix":49,"avg_A_prefix":6,"max_A_AS":1567,"avg_A_AS":45,"nb_orign_change":23,"nb_new_A":156,"nb_new_A_afterW":262,"max_path_len":21,"avg_path_len":5,"max_editdist":18,"avg_editdist":2,"editdist_7":45,"editdist_8":85,"editdist_9":19,"editdist_10":37,"editdist_11":8,"editdist_12":31,"editdist_13":5,"editdist_14":0,"editdist_15":0,"editdist_16":0,"editdist_17":16,"nb_tolonger":1649,"nb_toshorter":2749,"avg_interarrival":1123},{"nb_A":4485,"nb_W":377,"nb_implicit_W":3218,"nb_dup_A":781,"nb_dup_W":0,"nb_A_prefix":519,"nb_W_prefix":110,"max_A_prefix":46,"avg_A_prefix":9,"max_A_AS":1249,"avg_A_AS":32,"nb_orign_change":108,"nb_new_A":309,"nb_new_A_afterW":177,"max_path_len":16,"avg_path_len":5,"max_editdist":10,"avg_editdist":2,"editdist_7":19,"editdist_8":73,"editdist_9":54,"editdist_10":41,"editdist_11":0,"editdist_12":0,"editdist_13":0,"editdist_14":0,"editdist_15":0,"editdist_16":0,"editdist_17":0,"nb_tolonger":1103,"nb_toshorter":2115,"avg_interarrival":1102},{"nb_A":3346,"nb_W":368,"nb_implicit_W":2123,"nb_dup_A":843,"nb_dup_W":2,"nb_A_prefix":379,"nb_W_prefix":116,"max_A_prefix":48,"avg_A_prefix":9,"max_A_AS":684,"avg_A_AS":27,"nb_orign_change":75,"nb_new_A":210,"nb_new_A_afterW":170,"max_path_len":15,"avg_path_len":6,"max_editdist":11,"avg_editdist":2,"editdist_7":4,"editdist_8":0,"editdist_9":18,"editdist_10":9,"editdist_11":2,"editdist_12":0,"editdist_13":0,"editdist_14":0,"editdist_15":0,"editdist_16":0,"editdist_17":0,"nb_tolonger":722,"nb_toshorter":1401,"avg_interarrival":1092},{"nb_A":2532,"nb_W":312,"nb_implicit_W":1853,"nb_dup_A":433,"nb_dup_W":1,"nb_A_prefix":590,"nb_W_prefix":101,"max_A_prefix":37,"avg_A_prefix":4,"max_A_AS":548,"avg_A_AS":21,"nb_orign_change":21,"nb_new_A":145,"nb_new_A_afterW":101,"max_path_len":18,"avg_path_len":5,"max_editdist":8,"avg_editdist":2,"editdist_7":9,"editdist_8":9,"editdist_9":0,"editdist_10":0,"editdist_11":0,"editdist_12":0,"editdist_13":0,"editdist_14":0,"editdist_15":0,"editdist_16":0,"editdist_17":0,"nb_tolonger":392,"nb_toshorter":1461,"avg_interarrival":1112},{"nb_A":3182,"nb_W":329,"nb_implicit_W":2554,"nb_dup_A":385,"nb_dup_W":0,"nb_A_prefix":693,"nb_W_prefix":106,"max_A_prefix":36,"avg_A_prefix":5,"max_A_AS":1123,"avg_A_AS":27,"nb_orign_change":22,"nb_new_A":140,"nb_new_A_afterW":103,"max_path_len":15,"avg_path_len":5,"max_editdist":9,"avg_editdist":2,"editdist_7":41,"editdist_8":19,"editdist_9":4,"editdist_10":0,"editdist_11":0,"editdist_12":0,"editdist_13":0,"editdist_14":0,"editdist_15":0,"editdist_16":0,"editdist_17":0,"nb_tolonger":1177,"nb_toshorter":1377,"avg_interarrival":1092},{"nb_A":3616,"nb_W":259,"nb_implicit_W":2534,"nb_dup_A":655,"nb_dup_W":0,"nb_A_prefix":418,"nb_W_prefix":118,"max_A_prefix":33,"avg_A_prefix":9,"max_A_AS":912,"avg_A_AS":30,"nb_orign_change":41,"nb_new_A":313,"nb_new_A_afterW":114,"max_path_len":16,"avg_path_len":5,"max_editdist":10,"avg_editdist":2,"editdist_7":16,"editdist_8":1,"editdist_9":0,"editdist_10":3,"editdist_11":0,"editdist_12":0,"editdist_13":0,"editdist_14":0,"editdist_15":0,"editdist_16":0,"editdist_17":0,"nb_tolonger":926,"nb_toshorter":1608,"avg_interarrival":1112},{"nb_A":2428,"nb_W":282,"nb_implicit_W":1585,"nb_dup_A":449,"nb_dup_W":3,"nb_A_prefix":287,"nb_W_prefix":83,"max_A_prefix":44,"avg_A_prefix":8,"max_A_AS":164,"avg_A_AS":20,"nb_orign_change":29,"nb_new_A":279,"nb_new_A_afterW":115,"max_path_len":24,"avg_path_len":6,"max_editdist":13,"avg_editdist":2,"editdist_7":13,"editdist_8":0,"editdist_9":0,"editdist_10":1,"editdist_11":1,"editdist_12":0,"editdist_13":1,"editdist_14":0,"editdist_15":0,"editdist_16":0,"editdist_17":0,"nb_tolonger":655,"nb_toshorter":930,"avg_interarrival":1044},{"nb_A":2698,"nb_W":356,"nb_implicit_W":1662,"nb_dup_A":645,"nb_dup_W":1,"nb_A_prefix":423,"nb_W_prefix":128,"max_A_prefix":43,"avg_A_prefix":6,"max_A_AS":196,"avg_A_AS":20,"nb_orign_change":56,"nb_new_A":258,"nb_new_A_afterW":133,"max_path_len":36,"avg_path_len":6,"max_editdist":26,"avg_editdist":2,"editdist_7":8,"editdist_8":1,"editdist_9":6,"editdist_10":0,"editdist_11":3,"editdist_12":1,"editdist_13":1,"editdist_14":0,"editdist_15":0,"editdist_16":0,"editdist_17":0,"nb_tolonger":680,"nb_toshorter":982,"avg_interarrival":1155},{"nb_A":3530,"nb_W":282,"nb_implicit_W":2135,"nb_dup_A":1138,"nb_dup_W":0,"nb_A_prefix":436,"nb_W_prefix":67,"max_A_prefix":39,"avg_A_prefix":8,"max_A_AS":1068,"avg_A_AS":27,"nb_orign_change":7,"nb_new_A":177,"nb_new_A_afterW":80,"max_path_len":29,"avg_path_len":6,"max_editdist":17,"avg_editdist":2,"editdist_7":8,"editdist_8":35,"editdist_9":4,"editdist_10":3,"editdist_11":3,"editdist_12":0,"editdist_13":6,"editdist_14":0,"editdist_15":0,"editdist_16":0,"editdist_17":1,"nb_tolonger":910,"nb_toshorter":1225,"avg_interarrival":1167},{"nb_A":2325,"nb_W":291,"nb_implicit_W":1673,"nb_dup_A":484,"nb_dup_W":1,"nb_A_prefix":356,"nb_W_prefix":97,"max_A_prefix":53,"avg_A_prefix":7,"max_A_AS":661,"avg_A_AS":20,"nb_orign_change":14,"nb_new_A":58,"nb_new_A_afterW":110,"max_path_len":28,"avg_path_len":6,"max_editdist":13,"avg_editdist":2,"editdist_7":14,"editdist_8":16,"editdist_9":1,"editdist_10":0,"editdist_11":0,"editdist_12":2,"editdist_13":1,"editdist_14":0,"editdist_15":0,"editdist_16":0,"editdist_17":0,"nb_tolonger":612,"nb_toshorter":1061,"avg_interarrival":1123},{"nb_A":4301,"nb_W":272,"nb_implicit_W":2893,"nb_dup_A":1066,"nb_dup_W":0,"nb_A_prefix":890,"nb_W_prefix":125,"max_A_prefix":37,"avg_A_prefix":5,"max_A_AS":1582,"avg_A_AS":33,"nb_orign_change":51,"nb_new_A":228,"nb_new_A_afterW":114,"max_path_len":20,"avg_path_len":5,"max_editdist":17,"avg_editdist":2,"editdist_7":9,"editdist_8":36,"editdist_9":0,"editdist_10":0,"editdist_11":2,"editdist_12":1,"editdist_13":0,"editdist_14":0,"editdist_15":0,"editdist_16":0,"editdist_17":1,"nb_tolonger":1041,"nb_toshorter":1852,"avg_interarrival":1103},{"nb_A":2997,"nb_W":283,"nb_implicit_W":2135,"nb_dup_A":638,"nb_dup_W":1,"nb_A_prefix":335,"nb_W_prefix":96,"max_A_prefix":44,"avg_A_prefix":9,"max_A_AS":657,"avg_A_AS":26,"nb_orign_change":32,"nb_new_A":139,"nb_new_A_afterW":85,"max_path_len":14,"avg_path_len":6,"max_editdist":11,"avg_editdist":2,"editdist_7":34,"editdist_8":41,"editdist_9":37,"editdist_10":10,"editdist_11":1,"editdist_12":0,"editdist_13":0,"editdist_14":0,"editdist_15":0,"editdist_16":0,"editdist_17":0,"nb_tolonger":732,"nb_toshorter":1403,"avg_interarrival":1113},{"nb_A":3903,"nb_W":369,"nb_implicit_W":3017,"nb_dup_A":619,"nb_dup_W":1,"nb_A_prefix":505,"nb_W_prefix":201,"max_A_prefix":51,"avg_A_prefix":8,"max_A_AS":683,"avg_A_AS":31,"nb_orign_change":78,"nb_new_A":125,"nb_new_A_afterW":142,"max_path_len":24,"avg_path_len":5,"max_editdist":13,"avg_editdist":2,"editdist_7":20,"editdist_8":37,"editdist_9":13,"editdist_10":21,"editdist_11":4,"editdist_12":0,"editdist_13":3,"editdist_14":0,"editdist_15":0,"editdist_16":0,"editdist_17":0,"nb_tolonger":1416,"nb_toshorter":1601,"avg_interarrival":1123},{"nb_A":3944,"nb_W":370,"nb_implicit_W":2529,"nb_dup_A":773,"nb_dup_W":0,"nb_A_prefix":526,"nb_W_prefix":123,"max_A_prefix":41,"avg_A_prefix":7,"max_A_AS":686,"avg_A_AS":31,"nb_orign_change":15,"nb_new_A":457,"nb_new_A_afterW":185,"max_path_len":22,"avg_path_len":6,"max_editdist":17,"avg_editdist":2,"editdist_7":14,"editdist_8":3,"editdist_9":0,"editdist_10":5,"editdist_11":1,"editdist_12":13,"editdist_13":0,"editdist_14":0,"editdist_15":0,"editdist_16":0,"editdist_17":9,"nb_tolonger":878,"nb_toshorter":1651,"avg_interarrival":1093},{"nb_A":6085,"nb_W":367,"nb_implicit_W":4712,"nb_dup_A":1016,"nb_dup_W":1,"nb_A_prefix":931,"nb_W_prefix":122,"max_A_prefix":49,"avg_A_prefix":7,"max_A_AS":1376,"avg_A_AS":36,"nb_orign_change":36,"nb_new_A":229,"nb_new_A_afterW":128,"max_path_len":22,"avg_path_len":6,"max_editdist":19,"avg_editdist":2,"editdist_7":15,"editdist_8":5,"editdist_9":0,"editdist_10":14,"editdist_11":0,"editdist_12":8,"editdist_13":2,"editdist_14":4,"editdist_15":0,"editdist_16":0,"editdist_17":2,"nb_tolonger":1771,"nb_toshorter":2941,"avg_interarrival":1073},{"nb_A":3121,"nb_W":250,"nb_implicit_W":2377,"nb_dup_A":408,"nb_dup_W":0,"nb_A_prefix":436,"nb_W_prefix":77,"max_A_prefix":37,"avg_A_prefix":7,"max_A_AS":235,"avg_A_AS":21,"nb_orign_change":28,"nb_new_A":243,"nb_new_A_afterW":93,"max_path_len":24,"avg_path_len":6,"max_editdist":18,"avg_editdist":2,"editdist_7":17,"editdist_8":3,"editdist_9":0,"editdist_10":12,"editdist_11":0,"editdist_12":19,"editdist_13":2,"editdist_14":0,"editdist_15":3,"editdist_16":4,"editdist_17":8,"nb_tolonger":824,"nb_toshorter":1553,"avg_interarrival":1044},{"nb_A":5529,"nb_W":570,"nb_implicit_W":3371,"nb_dup_A":1530,"nb_dup_W":0,"nb_A_prefix":724,"nb_W_prefix":155,"max_A_prefix":45,"avg_A_prefix":8,"max_A_AS":1568,"avg_A_AS":29,"nb_orign_change":16,"nb_new_A":294,"nb_new_A_afterW":334,"max_path_len":19,"avg_path_len":6,"max_editdist":11,"avg_editdist":2,"editdist_7":26,"editdist_8":15,"editdist_9":30,"editdist_10":64,"editdist_11":1,"editdist_12":0,"editdist_13":0,"editdist_14":0,"editdist_15":0,"editdist_16":0,"editdist_17":0,"nb_tolonger":863,"nb_toshorter":2508,"avg_interarrival":1082},{"nb_A":13442,"nb_W":632,"nb_implicit_W":10872,"nb_dup_A":2080,"nb_dup_W":1,"nb_A_prefix":1085,"nb_W_prefix":163,"max_A_prefix":45,"avg_A_prefix":12,"max_A_AS":6154,"avg_A_AS":112,"nb_orign_change":8,"nb_new_A":208,"nb_new_A_afterW":282,"max_path_len":22,"avg_path_len":5,"max_editdist":12,"avg_editdist":2,"editdist_7":138,"editdist_8":104,"editdist_9":36,"editdist_10":44,"editdist_11":3,"editdist_12":1,"editdist_13":0,"editdist_14":0,"editdist_15":0,"editdist_16":0,"editdist_17":0,"nb_tolonger":2536,"nb_toshorter":8336,"avg_interarrival":1133},{"nb_A":8499,"nb_W":864,"nb_implicit_W":5493,"nb_dup_A":2535,"nb_dup_W":2,"nb_A_prefix":776,"nb_W_prefix":200,"max_A_prefix":47,"avg_A_prefix":11,"max_A_AS":2054,"avg_A_AS":53,"nb_orign_change":25,"nb_new_A":211,"nb_new_A_afterW":260,"max_path_len":15,"avg_path_len":5,"max_editdist":10,"avg_editdist":2,"editdist_7":55,"editdist_8":109,"editdist_9":62,"editdist_10":22,"editdist_11":0,"editdist_12":0,"editdist_13":0,"editdist_14":0,"editdist_15":0,"editdist_16":0,"editdist_17":0,"nb_tolonger":1757,"nb_toshorter":3736,"avg_interarrival":1112},{"nb_A":4571,"nb_W":328,"nb_implicit_W":2750,"nb_dup_A":1103,"nb_dup_W":0,"nb_A_prefix":430,"nb_W_prefix":109,"max_A_prefix":47,"avg_A_prefix":11,"max_A_AS":1253,"avg_A_AS":38,"nb_orign_change":236,"nb_new_A":595,"nb_new_A_afterW":123,"max_path_len":13,"avg_path_len":5,"max_editdist":11,"avg_editdist":2,"editdist_7":127,"editdist_8":0,"editdist_9":47,"editdist_10":18,"editdist_11":7,"editdist_12":0,"editdist_13":0,"editdist_14":0,"editdist_15":0,"editdist_16":0,"editdist_17":0,"nb_tolonger":775,"nb_toshorter":1975,"avg_interarrival":1102},{"nb_A":4538,"nb_W":262,"nb_implicit_W":3089,"nb_dup_A":1020,"nb_dup_W":0,"nb_A_prefix":890,"nb_W_prefix":116,"max_A_prefix":38,"avg_A_prefix":5,"max_A_AS":1613,"avg_A_AS":31,"nb_orign_change":105,"nb_new_A":351,"nb_new_A_afterW":78,"max_path_len":25,"avg_path_len":4,"max_editdist":26,"avg_editdist":2,"editdist_7":23,"editdist_8":5,"editdist_9":20,"editdist_10":21,"editdist_11":2,"editdist_12":0,"editdist_13":0,"editdist_14":0,"editdist_15":0,"editdist_16":0,"editdist_17":0,"nb_tolonger":1051,"nb_toshorter":2038,"avg_interarrival":1092},{"nb_A":2083,"nb_W":319,"nb_implicit_W":1325,"nb_dup_A":563,"nb_dup_W":2,"nb_A_prefix":231,"nb_W_prefix":94,"max_A_prefix":65,"avg_A_prefix":9,"max_A_AS":273,"avg_A_AS":18,"nb_orign_change":12,"nb_new_A":87,"nb_new_A_afterW":108,"max_path_len":28,"avg_path_len":5,"max_editdist":26,"avg_editdist":2,"editdist_7":13,"editdist_8":9,"editdist_9":17,"editdist_10":2,"editdist_11":2,"editdist_12":4,"editdist_13":1,"editdist_14":0,"editdist_15":0,"editdist_16":0,"editdist_17":0,"nb_tolonger":496,"nb_toshorter":829,"avg_interarrival":1133},{"nb_A":2194,"nb_W":353,"nb_implicit_W":1493,"nb_dup_A":498,"nb_dup_W":4,"nb_A_prefix":301,"nb_W_prefix":104,"max_A_prefix":46,"avg_A_prefix":7,"max_A_AS":264,"avg_A_AS":16,"nb_orign_change":120,"nb_new_A":98,"nb_new_A_afterW":105,"max_path_len":18,"avg_path_len":6,"max_editdist":11,"avg_editdist":3,"editdist_7":3,"editdist_8":43,"editdist_9":55,"editdist_10":32,"editdist_11":2,"editdist_12":0,"editdist_13":0,"editdist_14":0,"editdist_15":0,"editdist_16":0,"editdist_17":0,"nb_tolonger":527,"nb_toshorter":966,"avg_interarrival":1167},{"nb_A":2385,"nb_W":179,"nb_implicit_W":1612,"nb_dup_A":534,"nb_dup_W":0,"nb_A_prefix":399,"nb_W_prefix":59,"max_A_prefix":39,"avg_A_prefix":6,"max_A_AS":308,"avg_A_AS":19,"nb_orign_change":16,"nb_new_A":163,"nb_new_A_afterW":76,"max_path_len":14,"avg_path_len":6,"max_editdist":11,"avg_editdist":2,"editdist_7":29,"editdist_8":54,"editdist_9":19,"editdist_10":7,"editdist_11":1,"editdist_12":0,"editdist_13":0,"editdist_14":0,"editdist_15":0,"editdist_16":0,"editdist_17":0,"nb_tolonger":612,"nb_toshorter":1000,"avg_interarrival":1184},{"nb_A":12202,"nb_W":583,"nb_implicit_W":9922,"nb_dup_A":1905,"nb_dup_W":0,"nb_A_prefix":1010,"nb_W_prefix":182,"max_A_prefix":53,"avg_A_prefix":12,"max_A_AS":4946,"avg_A_AS":95,"nb_orign_change":45,"nb_new_A":156,"nb_new_A_afterW":219,"max_path_len":28,"avg_path_len":9,"max_editdist":22,"avg_editdist":5,"editdist_7":275,"editdist_8":280,"editdist_9":107,"editdist_10":18,"editdist_11":1307,"editdist_12":705,"editdist_13":182,"editdist_14":52,"editdist_15":4,"editdist_16":6,"editdist_17":8,"nb_tolonger":5928,"nb_toshorter":3994,"avg_interarrival":1072},{"nb_A":7905,"nb_W":1922,"nb_implicit_W":4804,"nb_dup_A":2321,"nb_dup_W":0,"nb_A_prefix":781,"nb_W_prefix":391,"max_A_prefix":54,"avg_A_prefix":10,"max_A_AS":3076,"avg_A_AS":43,"nb_orign_change":57,"nb_new_A":182,"nb_new_A_afterW":598,"max_path_len":23,"avg_path_len":9,"max_editdist":23,"avg_editdist":2,"editdist_7":21,"editdist_8":23,"editdist_9":9,"editdist_10":15,"editdist_11":184,"editdist_12":75,"editdist_13":35,"editdist_14":22,"editdist_15":6,"editdist_16":3,"editdist_17":8,"nb_tolonger":1269,"nb_toshorter":3535,"avg_interarrival":1053},{"nb_A":5669,"nb_W":1605,"nb_implicit_W":3665,"nb_dup_A":895,"nb_dup_W":2,"nb_A_prefix":840,"nb_W_prefix":333,"max_A_prefix":36,"avg_A_prefix":7,"max_A_AS":1967,"avg_A_AS":29,"nb_orign_change":36,"nb_new_A":723,"nb_new_A_afterW":386,"max_path_len":24,"avg_path_len":7,"max_editdist":17,"avg_editdist":3,"editdist_7":89,"editdist_8":111,"editdist_9":55,"editdist_10":26,"editdist_11":15,"editdist_12":70,"editdist_13":131,"editdist_14":8,"editdist_15":0,"editdist_16":8,"editdist_17":8,"nb_tolonger":1071,"nb_toshorter":2594,"avg_interarrival":1092},{"nb_A":6667,"nb_W":280,"nb_implicit_W":3606,"nb_dup_A":1216,"nb_dup_W":0,"nb_A_prefix":883,"nb_W_prefix":132,"max_A_prefix":52,"avg_A_prefix":8,"max_A_AS":2241,"avg_A_AS":51,"nb_orign_change":21,"nb_new_A":1700,"nb_new_A_afterW":145,"max_path_len":22,"avg_path_len":7,"max_editdist":17,"avg_editdist":3,"editdist_7":176,"editdist_8":164,"editdist_9":108,"editdist_10":14,"editdist_11":28,"editdist_12":61,"editdist_13":8,"editdist_14":2,"editdist_15":0,"editdist_16":0,"editdist_17":6,"nb_tolonger":936,"nb_toshorter":2670,"avg_interarrival":1155},{"nb_A":3326,"nb_W":328,"nb_implicit_W":2110,"nb_dup_A":746,"nb_dup_W":2,"nb_A_prefix":558,"nb_W_prefix":99,"max_A_prefix":55,"avg_A_prefix":6,"max_A_AS":424,"avg_A_AS":25,"nb_orign_change":180,"nb_new_A":277,"nb_new_A_afterW":193,"max_path_len":18,"avg_path_len":5,"max_editdist":13,"avg_editdist":2,"editdist_7":41,"editdist_8":20,"editdist_9":1,"editdist_10":1,"editdist_11":11,"editdist_12":1,"editdist_13":1,"editdist_14":0,"editdist_15":0,"editdist_16":0,"editdist_17":0,"nb_tolonger":713,"nb_toshorter":1397,"avg_interarrival":1135},{"nb_A":6512,"nb_W":530,"nb_implicit_W":4852,"nb_dup_A":1187,"nb_dup_W":0,"nb_A_prefix":752,"nb_W_prefix":238,"max_A_prefix":47,"avg_A_prefix":9,"max_A_AS":1402,"avg_A_AS":52,"nb_orign_change":39,"nb_new_A":158,"nb_new_A_afterW":315,"max_path_len":26,"avg_path_len":6,"max_editdist":23,"avg_editdist":3,"editdist_7":142,"editdist_8":25,"editdist_9":19,"editdist_10":4,"editdist_11":43,"editdist_12":2,"editdist_13":3,"editdist_14":2,"editdist_15":1,"editdist_16":0,"editdist_17":0,"nb_tolonger":2311,"nb_toshorter":2541,"avg_interarrival":1054},{"nb_A":11308,"nb_W":1154,"nb_implicit_W":8762,"nb_dup_A":1973,"nb_dup_W":0,"nb_A_prefix":1308,"nb_W_prefix":364,"max_A_prefix":41,"avg_A_prefix":9,"max_A_AS":3142,"avg_A_AS":77,"nb_orign_change":50,"nb_new_A":124,"nb_new_A_afterW":449,"max_path_len":27,"avg_path_len":8,"max_editdist":23,"avg_editdist":4,"editdist_7":285,"editdist_8":170,"editdist_9":85,"editdist_10":5,"editdist_11":1184,"editdist_12":394,"editdist_13":141,"editdist_14":47,"editdist_15":4,"editdist_16":6,"editdist_17":16,"nb_tolonger":4857,"nb_toshorter":3905,"avg_interarrival":1082},{"nb_A":9930,"nb_W":1972,"nb_implicit_W":6062,"nb_dup_A":1272,"nb_dup_W":0,"nb_A_prefix":731,"nb_W_prefix":284,"max_A_prefix":42,"avg_A_prefix":14,"max_A_AS":3369,"avg_A_AS":64,"nb_orign_change":93,"nb_new_A":803,"nb_new_A_afterW":1793,"max_path_len":26,"avg_path_len":8,"max_editdist":24,"avg_editdist":4,"editdist_7":324,"editdist_8":201,"editdist_9":125,"editdist_10":80,"editdist_11":14,"editdist_12":235,"editdist_13":137,"editdist_14":6,"editdist_15":2,"editdist_16":0,"editdist_17":8,"nb_tolonger":1050,"nb_toshorter":5012,"avg_interarrival":1035},{"nb_A":8772,"nb_W":486,"nb_implicit_W":4174,"nb_dup_A":4314,"nb_dup_W":9,"nb_A_prefix":3303,"nb_W_prefix":158,"max_A_prefix":47,"avg_A_prefix":3,"max_A_AS":1538,"avg_A_AS":13,"nb_orign_change":25,"nb_new_A":123,"nb_new_A_afterW":161,"max_path_len":31,"avg_path_len":6,"max_editdist":29,"avg_editdist":3,"editdist_7":114,"editdist_8":69,"editdist_9":54,"editdist_10":27,"editdist_11":53,"editdist_12":23,"editdist_13":64,"editdist_14":1,"editdist_15":5,"editdist_16":0,"editdist_17":4,"nb_tolonger":2008,"nb_toshorter":2166,"avg_interarrival":1035},{"nb_A":7304,"nb_W":992,"nb_implicit_W":5681,"nb_dup_A":1202,"nb_dup_W":2,"nb_A_prefix":877,"nb_W_prefix":384,"max_A_prefix":46,"avg_A_prefix":8,"max_A_AS":2214,"avg_A_AS":47,"nb_orign_change":126,"nb_new_A":199,"nb_new_A_afterW":222,"max_path_len":28,"avg_path_len":9,"max_editdist":23,"avg_editdist":5,"editdist_7":180,"editdist_8":110,"editdist_9":110,"editdist_10":41,"editdist_11":894,"editdist_12":472,"editdist_13":102,"editdist_14":38,"editdist_15":15,"editdist_16":9,"editdist_17":15,"nb_tolonger":3578,"nb_toshorter":2103,"avg_interarrival":1092},{"nb_A":7549,"nb_W":2850,"nb_implicit_W":5528,"nb_dup_A":1499,"nb_dup_W":8,"nb_A_prefix":1013,"nb_W_prefix":449,"max_A_prefix":48,"avg_A_prefix":7,"max_A_AS":1796,"avg_A_AS":52,"nb_orign_change":52,"nb_new_A":142,"nb_new_A_afterW":380,"max_path_len":31,"avg_path_len":8,"max_editdist":28,"avg_editdist":2,"editdist_7":9,"editdist_8":82,"editdist_9":48,"editdist_10":10,"editdist_11":16,"editdist_12":40,"editdist_13":19,"editdist_14":2,"editdist_15":4,"editdist_16":2,"editdist_17":11,"nb_tolonger":1957,"nb_toshorter":3571,"avg_interarrival":1114},{"nb_A":12918,"nb_W":736,"nb_implicit_W":6614,"nb_dup_A":3222,"nb_dup_W":3,"nb_A_prefix":1574,"nb_W_prefix":220,"max_A_prefix":44,"avg_A_prefix":8,"max_A_AS":2488,"avg_A_AS":65,"nb_orign_change":101,"nb_new_A":2839,"nb_new_A_afterW":243,"max_path_len":25,"avg_path_len":7,"max_editdist":16,"avg_editdist":3,"editdist_7":87,"editdist_8":93,"editdist_9":71,"editdist_10":42,"editdist_11":22,"editdist_12":8,"editdist_13":2,"editdist_14":3,"editdist_15":0,"editdist_16":7,"editdist_17":0,"nb_tolonger":2373,"nb_toshorter":4241,"avg_interarrival":1072},{"nb_A":5456,"nb_W":537,"nb_implicit_W":3816,"nb_dup_A":983,"nb_dup_W":0,"nb_A_prefix":825,"nb_W_prefix":283,"max_A_prefix":38,"avg_A_prefix":7,"max_A_AS":987,"avg_A_AS":31,"nb_orign_change":28,"nb_new_A":507,"nb_new_A_afterW":150,"max_path_len":23,"avg_path_len":6,"max_editdist":18,"avg_editdist":2,"editdist_7":54,"editdist_8":31,"editdist_9":7,"editdist_10":27,"editdist_11":21,"editdist_12":27,"editdist_13":13,"editdist_14":0,"editdist_15":2,"editdist_16":0,"editdist_17":2,"nb_tolonger":1157,"nb_toshorter":2659,"avg_interarrival":1123},{"nb_A":4284,"nb_W":502,"nb_implicit_W":2953,"nb_dup_A":932,"nb_dup_W":0,"nb_A_prefix":581,"nb_W_prefix":176,"max_A_prefix":35,"avg_A_prefix":7,"max_A_AS":742,"avg_A_AS":24,"nb_orign_change":19,"nb_new_A":268,"nb_new_A_afterW":131,"max_path_len":16,"avg_path_len":6,"max_editdist":13,"avg_editdist":2,"editdist_7":15,"editdist_8":8,"editdist_9":3,"editdist_10":0,"editdist_11":2,"editdist_12":5,"editdist_13":3,"editdist_14":0,"editdist_15":0,"editdist_16":0,"editdist_17":0,"nb_tolonger":1028,"nb_toshorter":1925,"avg_interarrival":1123},{"nb_A":3392,"nb_W":375,"nb_implicit_W":2428,"nb_dup_A":633,"nb_dup_W":0,"nb_A_prefix":431,"nb_W_prefix":129,"max_A_prefix":40,"avg_A_prefix":8,"max_A_AS":726,"avg_A_AS":23,"nb_orign_change":44,"nb_new_A":223,"nb_new_A_afterW":108,"max_path_len":18,"avg_path_len":6,"max_editdist":13,"avg_editdist":2,"editdist_7":23,"editdist_8":20,"editdist_9":1,"editdist_10":10,"editdist_11":2,"editdist_12":11,"editdist_13":1,"editdist_14":0,"editdist_15":0,"editdist_16":0,"editdist_17":0,"nb_tolonger":933,"nb_toshorter":1495,"avg_interarrival":1102},{"nb_A":3556,"nb_W":339,"nb_implicit_W":2478,"nb_dup_A":798,"nb_dup_W":0,"nb_A_prefix":435,"nb_W_prefix":124,"max_A_prefix":48,"avg_A_prefix":8,"max_A_AS":778,"avg_A_AS":27,"nb_orign_change":12,"nb_new_A":138,"nb_new_A_afterW":142,"max_path_len":17,"avg_path_len":6,"max_editdist":13,"avg_editdist":2,"editdist_7":23,"editdist_8":3,"editdist_9":2,"editdist_10":10,"editdist_11":0,"editdist_12":10,"editdist_13":1,"editdist_14":0,"editdist_15":0,"editdist_16":0,"editdist_17":0,"nb_tolonger":1005,"nb_toshorter":1473,"avg_interarrival":1092},{"nb_A":6052,"nb_W":411,"nb_implicit_W":4450,"nb_dup_A":1232,"nb_dup_W":0,"nb_A_prefix":1159,"nb_W_prefix":247,"max_A_prefix":36,"avg_A_prefix":5,"max_A_AS":2034,"avg_A_AS":32,"nb_orign_change":16,"nb_new_A":71,"nb_new_A_afterW":299,"max_path_len":18,"avg_path_len":5,"max_editdist":13,"avg_editdist":2,"editdist_7":30,"editdist_8":15,"editdist_9":9,"editdist_10":11,"editdist_11":9,"editdist_12":11,"editdist_13":8,"editdist_14":0,"editdist_15":0,"editdist_16":0,"editdist_17":0,"nb_tolonger":1965,"nb_toshorter":2485,"avg_interarrival":1190},{"nb_A":5533,"nb_W":344,"nb_implicit_W":3565,"nb_dup_A":1544,"nb_dup_W":0,"nb_A_prefix":622,"nb_W_prefix":158,"max_A_prefix":41,"avg_A_prefix":9,"max_A_AS":1068,"avg_A_AS":37,"nb_orign_change":106,"nb_new_A":210,"nb_new_A_afterW":214,"max_path_len":16,"avg_path_len":5,"max_editdist":15,"avg_editdist":2,"editdist_7":26,"editdist_8":32,"editdist_9":18,"editdist_10":8,"editdist_11":7,"editdist_12":2,"editdist_13":0,"editdist_14":0,"editdist_15":16,"editdist_16":0,"editdist_17":0,"nb_tolonger":1048,"nb_toshorter":2517,"avg_interarrival":1044},{"nb_A":10448,"nb_W":1367,"nb_implicit_W":7603,"nb_dup_A":1904,"nb_dup_W":0,"nb_A_prefix":825,"nb_W_prefix":410,"max_A_prefix":38,"avg_A_prefix":13,"max_A_AS":2996,"avg_A_AS":67,"nb_orign_change":1116,"nb_new_A":149,"nb_new_A_afterW":792,"max_path_len":17,"avg_path_len":7,"max_editdist":12,"avg_editdist":3,"editdist_7":759,"editdist_8":223,"editdist_9":14,"editdist_10":111,"editdist_11":68,"editdist_12":3,"editdist_13":0,"editdist_14":0,"editdist_15":0,"editdist_16":0,"editdist_17":0,"nb_tolonger":2743,"nb_toshorter":4860,"avg_interarrival":1054},{"nb_A":25070,"nb_W":1797,"nb_implicit_W":18932,"nb_dup_A":4431,"nb_dup_W":1,"nb_A_prefix":1915,"nb_W_prefix":525,"max_A_prefix":40,"avg_A_prefix":13,"max_A_AS":6975,"avg_A_AS":143,"nb_orign_change":1296,"nb_new_A":548,"nb_new_A_afterW":1159,"max_path_len":22,"avg_path_len":7,"max_editdist":15,"avg_editdist":3,"editdist_7":959,"editdist_8":313,"editdist_9":40,"editdist_10":56,"editdist_11":174,"editdist_12":247,"editdist_13":2,"editdist_14":12,"editdist_15":8,"editdist_16":0,"editdist_17":0,"nb_tolonger":8487,"nb_toshorter":10445,"avg_interarrival":1017},{"nb_A":9744,"nb_W":763,"nb_implicit_W":6773,"nb_dup_A":2345,"nb_dup_W":0,"nb_A_prefix":1624,"nb_W_prefix":358,"max_A_prefix":39,"avg_A_prefix":6,"max_A_AS":1431,"avg_A_AS":62,"nb_orign_change":964,"nb_new_A":339,"nb_new_A_afterW":287,"max_path_len":18,"avg_path_len":6,"max_editdist":15,"avg_editdist":3,"editdist_7":624,"editdist_8":137,"editdist_9":111,"editdist_10":0,"editdist_11":131,"editdist_12":2,"editdist_13":1,"editdist_14":0,"editdist_15":11,"editdist_16":0,"editdist_17":0,"nb_tolonger":1378,"nb_toshorter":5395,"avg_interarrival":1092},{"nb_A":3911,"nb_W":378,"nb_implicit_W":2808,"nb_dup_A":788,"nb_dup_W":0,"nb_A_prefix":655,"nb_W_prefix":161,"max_A_prefix":38,"avg_A_prefix":6,"max_A_AS":327,"avg_A_AS":24,"nb_orign_change":161,"nb_new_A":118,"nb_new_A_afterW":197,"max_path_len":24,"avg_path_len":6,"max_editdist":17,"avg_editdist":2,"editdist_7":138,"editdist_8":50,"editdist_9":24,"editdist_10":0,"editdist_11":2,"editdist_12":2,"editdist_13":0,"editdist_14":0,"editdist_15":0,"editdist_16":0,"editdist_17":1,"nb_tolonger":1034,"nb_toshorter":1774,"avg_interarrival":1072},{"nb_A":6227,"nb_W":512,"nb_implicit_W":5011,"nb_dup_A":743,"nb_dup_W":10,"nb_A_prefix":800,"nb_W_prefix":193,"max_A_prefix":42,"avg_A_prefix":8,"max_A_AS":801,"avg_A_AS":44,"nb_orign_change":80,"nb_new_A":253,"nb_new_A_afterW":220,"max_path_len":23,"avg_path_len":6,"max_editdist":18,"avg_editdist":3,"editdist_7":93,"editdist_8":61,"editdist_9":30,"editdist_10":28,"editdist_11":30,"editdist_12":4,"editdist_13":1,"editdist_14":0,"editdist_15":0,"editdist_16":0,"editdist_17":1,"nb_tolonger":1717,"nb_toshorter":3294,"avg_interarrival":1063},{"nb_A":5238,"nb_W":481,"nb_implicit_W":4090,"nb_dup_A":742,"nb_dup_W":0,"nb_A_prefix":874,"nb_W_prefix":162,"max_A_prefix":47,"avg_A_prefix":6,"max_A_AS":709,"avg_A_AS":32,"nb_orign_change":64,"nb_new_A":246,"nb_new_A_afterW":160,"max_path_len":23,"avg_path_len":6,"max_editdist":13,"avg_editdist":2,"editdist_7":118,"editdist_8":59,"editdist_9":17,"editdist_10":0,"editdist_11":11,"editdist_12":11,"editdist_13":1,"editdist_14":0,"editdist_15":0,"editdist_16":0,"editdist_17":0,"nb_tolonger":1281,"nb_toshorter":2809,"avg_interarrival":1092},{"nb_A":4715,"nb_W":718,"nb_implicit_W":3123,"nb_dup_A":1106,"nb_dup_W":1,"nb_A_prefix":741,"nb_W_prefix":183,"max_A_prefix":52,"avg_A_prefix":6,"max_A_AS":495,"avg_A_AS":24,"nb_orign_change":86,"nb_new_A":265,"nb_new_A_afterW":221,"max_path_len":25,"avg_path_len":6,"max_editdist":19,"avg_editdist":2,"editdist_7":52,"editdist_8":15,"editdist_9":7,"editdist_10":3,"editdist_11":12,"editdist_12":2,"editdist_13":0,"editdist_14":0,"editdist_15":2,"editdist_16":0,"editdist_17":0,"nb_tolonger":1290,"nb_toshorter":1833,"avg_interarrival":1072},{"nb_A":5190,"nb_W":385,"nb_implicit_W":3906,"nb_dup_A":916,"nb_dup_W":2,"nb_A_prefix":764,"nb_W_prefix":159,"max_A_prefix":39,"avg_A_prefix":7,"max_A_AS":617,"avg_A_AS":29,"nb_orign_change":23,"nb_new_A":257,"nb_new_A_afterW":111,"max_path_len":27,"avg_path_len":6,"max_editdist":18,"avg_editdist":3,"editdist_7":106,"editdist_8":36,"editdist_9":18,"editdist_10":31,"editdist_11":15,"editdist_12":10,"editdist_13":24,"editdist_14":3,"editdist_15":6,"editdist_16":0,"editdist_17":0,"nb_tolonger":1044,"nb_toshorter":2862,"avg_interarrival":1083},{"nb_A":6318,"nb_W":546,"nb_implicit_W":4473,"nb_dup_A":1007,"nb_dup_W":2,"nb_A_prefix":1199,"nb_W_prefix":246,"max_A_prefix":46,"avg_A_prefix":5,"max_A_AS":1557,"avg_A_AS":37,"nb_orign_change":35,"nb_new_A":582,"nb_new_A_afterW":256,"max_path_len":27,"avg_path_len":5,"max_editdist":12,"avg_editdist":2,"editdist_7":58,"editdist_8":48,"editdist_9":12,"editdist_10":12,"editdist_11":6,"editdist_12":8,"editdist_13":0,"editdist_14":0,"editdist_15":0,"editdist_16":0,"editdist_17":0,"nb_tolonger":1568,"nb_toshorter":2905,"avg_interarrival":1123},{"nb_A":5367,"nb_W":444,"nb_implicit_W":3627,"nb_dup_A":827,"nb_dup_W":2,"nb_A_prefix":817,"nb_W_prefix":139,"max_A_prefix":41,"avg_A_prefix":7,"max_A_AS":585,"avg_A_AS":29,"nb_orign_change":83,"nb_new_A":767,"nb_new_A_afterW":146,"max_path_len":22,"avg_path_len":6,"max_editdist":13,"avg_editdist":2,"editdist_7":14,"editdist_8":11,"editdist_9":18,"editdist_10":15,"editdist_11":51,"editdist_12":21,"editdist_13":6,"editdist_14":0,"editdist_15":0,"editdist_16":0,"editdist_17":0,"nb_tolonger":1184,"nb_toshorter":2443,"avg_interarrival":1123},{"nb_A":3733,"nb_W":390,"nb_implicit_W":2619,"nb_dup_A":487,"nb_dup_W":1,"nb_A_prefix":595,"nb_W_prefix":152,"max_A_prefix":40,"avg_A_prefix":6,"max_A_AS":867,"avg_A_AS":26,"nb_orign_change":6,"nb_new_A":454,"nb_new_A_afterW":173,"max_path_len":18,"avg_path_len":6,"max_editdist":14,"avg_editdist":2,"editdist_7":51,"editdist_8":28,"editdist_9":0,"editdist_10":5,"editdist_11":3,"editdist_12":1,"editdist_13":2,"editdist_14":2,"editdist_15":0,"editdist_16":0,"editdist_17":0,"nb_tolonger":798,"nb_toshorter":1821,"avg_interarrival":1092},{"nb_A":5794,"nb_W":725,"nb_implicit_W":3652,"nb_dup_A":1566,"nb_dup_W":0,"nb_A_prefix":680,"nb_W_prefix":215,"max_A_prefix":43,"avg_A_prefix":9,"max_A_AS":821,"avg_A_AS":43,"nb_orign_change":90,"nb_new_A":324,"nb_new_A_afterW":252,"max_path_len":21,"avg_path_len":6,"max_editdist":15,"avg_editdist":2,"editdist_7":44,"editdist_8":8,"editdist_9":25,"editdist_10":10,"editdist_11":78,"editdist_12":4,"editdist_13":1,"editdist_14":0,"editdist_15":2,"editdist_16":0,"editdist_17":0,"nb_tolonger":1844,"nb_toshorter":1808,"avg_interarrival":1072},{"nb_A":5545,"nb_W":316,"nb_implicit_W":3876,"nb_dup_A":1130,"nb_dup_W":1,"nb_A_prefix":1081,"nb_W_prefix":145,"max_A_prefix":41,"avg_A_prefix":5,"max_A_AS":1437,"avg_A_AS":38,"nb_orign_change":52,"nb_new_A":381,"nb_new_A_afterW":158,"max_path_len":18,"avg_path_len":5,"max_editdist":17,"avg_editdist":2,"editdist_7":39,"editdist_8":15,"editdist_9":12,"editdist_10":6,"editdist_11":7,"editdist_12":22,"editdist_13":2,"editdist_14":1,"editdist_15":0,"editdist_16":0,"editdist_17":4,"nb_tolonger":948,"nb_toshorter":2928,"avg_interarrival":1053},{"nb_A":5365,"nb_W":486,"nb_implicit_W":3877,"nb_dup_A":980,"nb_dup_W":0,"nb_A_prefix":648,"nb_W_prefix":167,"max_A_prefix":44,"avg_A_prefix":8,"max_A_AS":1134,"avg_A_AS":37,"nb_orign_change":485,"nb_new_A":258,"nb_new_A_afterW":250,"max_path_len":21,"avg_path_len":6,"max_editdist":12,"avg_editdist":3,"editdist_7":286,"editdist_8":98,"editdist_9":1,"editdist_10":39,"editdist_11":37,"editdist_12":20,"editdist_13":0,"editdist_14":0,"editdist_15":0,"editdist_16":0,"editdist_17":0,"nb_tolonger":1322,"nb_toshorter":2555,"avg_interarrival":1044},{"nb_A":10898,"nb_W":535,"nb_implicit_W":7096,"nb_dup_A":3347,"nb_dup_W":6,"nb_A_prefix":1386,"nb_W_prefix":150,"max_A_prefix":54,"avg_A_prefix":8,"max_A_AS":1944,"avg_A_AS":44,"nb_orign_change":78,"nb_new_A":212,"nb_new_A_afterW":243,"max_path_len":22,"avg_path_len":6,"max_editdist":14,"avg_editdist":2,"editdist_7":72,"editdist_8":38,"editdist_9":3,"editdist_10":15,"editdist_11":34,"editdist_12":2,"editdist_13":4,"editdist_14":1,"editdist_15":0,"editdist_16":0,"editdist_17":0,"nb_tolonger":3041,"nb_toshorter":4055,"avg_interarrival":1017},{"nb_A":7733,"nb_W":383,"nb_implicit_W":3552,"nb_dup_A":3659,"nb_dup_W":2,"nb_A_prefix":1802,"nb_W_prefix":130,"max_A_prefix":48,"avg_A_prefix":4,"max_A_AS":1198,"avg_A_AS":24,"nb_orign_change":28,"nb_new_A":380,"nb_new_A_afterW":142,"max_path_len":20,"avg_path_len":5,"max_editdist":13,"avg_editdist":2,"editdist_7":11,"editdist_8":5,"editdist_9":2,"editdist_10":3,"editdist_11":20,"editdist_12":1,"editdist_13":1,"editdist_14":0,"editdist_15":0,"editdist_16":0,"editdist_17":0,"nb_tolonger":868,"nb_toshorter":2684,"avg_interarrival":1102},{"nb_A":31489,"nb_W":405,"nb_implicit_W":7785,"nb_dup_A":23370,"nb_dup_W":1,"nb_A_prefix":22788,"nb_W_prefix":199,"max_A_prefix":35,"avg_A_prefix":1,"max_A_AS":1318,"avg_A_AS":14,"nb_orign_change":141,"nb_new_A":185,"nb_new_A_afterW":149,"max_path_len":25,"avg_path_len":5,"max_editdist":17,"avg_editdist":2,"editdist_7":51,"editdist_8":49,"editdist_9":1,"editdist_10":1,"editdist_11":66,"editdist_12":7,"editdist_13":29,"editdist_14":0,"editdist_15":0,"editdist_16":3,"editdist_17":5,"nb_tolonger":1626,"nb_toshorter":6159,"avg_interarrival":1026}]